mpcover/__init__.py
mpcover/__main__.py
mpcover/config.py
mpcover/connection.py
mpcover/controler.py
mpcover/gui/__init__.py
mpcover/gui/root.py
mpcover-0.3.0.dist-info/LICENSE
mpcover-0.3.0.dist-info/METADATA
mpcover-0.3.0.dist-info/WHEEL
mpcover-0.3.0.dist-info/entry_points.txt
mpcover-0.3.0.dist-info/RECORD
