Metadata-Version: 2.1
Name: mpcover
Version: 0.3.0
Summary: Python program for displaying album covers of music currently playing through MPD.
Author: Uroš Milivojević
Author-email: milivojevicu1998@gmail.com
Requires-Python: >=3.8.0,<4.0.0
Classifier: Programming Language :: Python :: 3
Classifier: Programming Language :: Python :: 3.8
Classifier: Programming Language :: Python :: 3.9
Classifier: Programming Language :: Python :: 3.10
Classifier: Programming Language :: Python :: 3.11
Requires-Dist: Pillow (>=10.0.0,<11.0.0)
